llm_transformers.py
llm_transformers-0.1.0.dist-info/METADATA
llm_transformers-0.1.0.dist-info/WHEEL
llm_transformers-0.1.0.dist-info/entry_points.txt
llm_transformers-0.1.0.dist-info/licenses/LICENSE
llm_transformers-0.1.0.dist-info/RECORD
