Metadata-Version: 2.3
Name: llm-transformers
Version: 0.1.0
Summary: Plugin for llm adding support for 🤗 Hugging Face Transformers
Project-URL: Homepage, https://github.com/rectalogic/llm-transformers
Project-URL: Changelog, https://github.com/rectalogic/llm-transformers/releases
Project-URL: Issues, https://github.com/rectalogic/llm-transformers/issues
Project-URL: CI, https://github.com/rectalogic/llm-transformers/actions
Author: Andrew Wason
License: Apache-2.0
License-File: LICENSE
Classifier: License :: OSI Approved :: Apache Software License
Requires-Python: >=3.12
Requires-Dist: av~=13.0.0
Requires-Dist: llm~=0.16
Requires-Dist: numpy~=2.1.1
Requires-Dist: pandas~=2.2.3
Requires-Dist: pillow~=10.4.0
Requires-Dist: protobuf~=5.28.2
Requires-Dist: pytesseract~=0.3.13
Requires-Dist: soundfile~=0.12.1
Requires-Dist: timm~=1.0.9
Requires-Dist: torch~=2.4.1
Requires-Dist: transformers~=4.45.1
